{
  "name" : "323_Data_Flow_Task",
  "type" : "Microsoft.DataFactory/factories/dataflows",
  "apiVersion" : "2018-06-01",
  "properties" : {
    "type" : "MappingDataFlow",
    "folder" : {
      "name" : "ssistoadf/demo1/Vulnerability_ETL_v2022"
    },
    "typeProperties" : {
      "sources" : [ {
        "name" : "OOBReport",
        "dataset" : {
          "referenceName" : "Excel1",
          "type" : "DatasetReference"
        }
      } ],
      "sinks" : [ ],
      "transformations" : [ {
        "name" : "DerivedColumn"
      } ],
      "script" : "\n\nsource(output(\n\t\tVIIDWFGUID as string,\n\t\tTCOO as string,\n\t\tCTO as string,\n\t\t{505_Indicator} as string,\n\t\t{505_Indicator__copy_} as string,\n\t\tAdj_Consequence_Model_Escalation_Date as date 'dd-MM-yyyy',\n\t\tADJUSTED_CM_DT as date 'dd-MM-yyyy',\n\t\tApplication_Support as string,\n\t\tApproved_Deferred_Remediation_Date as date 'dd-MM-yyyy',\n\t\tApproved_Deferred_Remediation_Dt as date 'dd-MM-yyyy',\n\t\tAsset_Class as string,\n\t\tAsset_SubClass as string,\n\t\tASSET_CI_TYPE as string,\n\t\tCI_Name as string,\n\t\tCIO_Direct_Org as string,\n\t\tCM_Intake_Filter as boolean,\n\t\tCM_Vulnerability_GroupID as string,\n\t\tCM_CR_DATE as string,\n\t\tCM_INTAKE_DATE as date 'dd-MM-yyyy',\n\t\tCM_Intake_Flag as boolean,\n\t\tCM_PRE_EXCEPTION_NUMBER as string,\n\t\tCM_VAT_FALSE_POSITIVE as string,\n\t\tCompliance_Status as boolean,\n\t\tConsequence_Model_Escalation_Date as date 'dd-MM-yyyy',\n\t\tData_ID_concat as string,\n\t\tData_Valid_Concat as string,\n\t\tData_Validation_ID as double,\n\t\tDataSource as string,\n\t\tDatasource_Check as double,\n\t\tDate_Logic as boolean,\n\t\tDeferred_Remediation_Date as string,\n\t\tDMAN_EVENT_PRIMARY_APP_NM as string,\n\t\tDomain as string,\n\t\tDRD_Approval_Status as string,\n\t\tDRD_Jira__ as string,\n\t\tEscalation as string,\n\t\tEscalation_Period as string,\n\t\tException_Number as string,\n\t\tGame_Plan_Link as string,\n\t\tHPSA_Mesh_Details as string,\n\t\tJAVA_PATH_ID as string,\n\t\tLast_Update_Date as date 'dd-MM-yyyy',\n\t\tManaged_By as string,\n\t\tMiddleware_Support as string,\n\t\tNon_Path as double,\n\t\tNumber_of_Records as double,\n\t\tOS_Maintenance_Support as string,\n\t\tOverdueVulnInstanceCount as double,\n\t\tOwned_By as string,\n\t\tPAI_Flag as boolean,\n\t\tPath as string,\n\t\tPath_Ind as string,\n\t\tPath_Vuln_Chk as double,\n\t\tPath_ProductName as string,\n\t\tPending_Escalation as boolean,\n\t\tPRB_Numb as string,\n\t\tPRB_Number as string,\n\t\tPRM_ as string,\n\t\tProduct_Name as string,\n\t\tPW_Exception_ID as string,\n\t\tPW_Expiration_Date as string,\n\t\tPW_Expiration_Dt as string,\n\t\tPW_Overall_Status as string,\n\t\tQID as double,\n\t\tQID_Title as string,\n\t\tQualysResults as string,\n\t\tQyls_First_Detected as date 'dd-MM-yyyy',\n\t\tQyls_Last_Detected as date 'dd-MM-yyyy',\n\t\tQyls_Vuln_Status as string,\n\t\tRC_Assignment as string,\n\t\tRC_Due_Date as date 'dd-MM-yyyy',\n\t\tRecord_Creation_Date as date 'dd-MM-yyyy',\n\t\tRemed_CR_Number as string,\n\t\tREMED_COMPETENCY_CENTER_COMMENTS_DESC as string,\n\t\tREMED_QVRU_ASSET_CLASS_NM as string,\n\t\tREMED_RESEARCH_COMMENTS_DESC as string,\n\t\tREMED_VO_DATA_ISSUE_NM as string,\n\t\tRemediation_CR_Number as string,\n\t\tReportRunDate as date 'dd-MM-yyyy',\n\t\tSN_CIO as string,\n\t\tSN_LOB as string,\n\t\tSN_Status as string,\n\t\tSN_CR_NUMBER as string,\n\t\tSolution_Plan as string,\n\t\tSolution_Plan_Indicator as boolean,\n\t\tSpecial_Care_Add_Date as date 'dd-MM-yyyy',\n\t\tSystem_Role as string,\n\t\tTarget_Remediation_Date as date 'dd-MM-yyyy',\n\t\tTarget_Remediation_Dt as date 'dd-MM-yyyy',\n\t\tTechnology_Manager as string,\n\t\tToday_dt as date 'dd-MM-yyyy',\n\t\ttoday_ as date 'dd-MM-yyyy',\n\t\tTSC_TECHNOPEDIA_ID as string,\n\t\tValidation_Description as string,\n\t\tVersion as string,\n\t\tVIID as string,\n\t\tVIIDWFGUID2 as string,\n\t\tVIIDWFGUID___Path as string,\n\t\tVIIDWFGUID___Path_Count as double,\n\t\tVIIDWFGUID_Path_Vulns as string,\n\t\tVIIDWFGUID_w_o_Path_Vulns as string,\n\t\tVIIDWFGUID_JAVAPATH as string,\n\t\tVMT_Competency as string,\n\t\tVO_Remediation_Status as string,\n\t\tVO_Remediation_Type as string,\n\t\tVO_Remediation_Type___VO_Remediation_Status as string,\n\t\tVO_Remediation_Type___VO_Rememdiation_Staus_Chk as double,\n\t\tVULN_SUB_CATEGORY_NM as string,\n\t\tVulnerability_Type as string,\n\t\tVulnInstance_Count as string,\n\t\tWF_Fix as string,\n\t\tWF_Rating as string,\n\t\tWFGUID as string,\n\t\tWO_Number as string,\n\t\tWS_Workstream_Name as string,\n\t\tWS_Workstream_POC as string,\n\t\tYear_of_ReportRunDate as double,\n\t\tZ_VulnType as string,\n\t\tz1_1 as string,\n\t\tz1_2 as string,\n\t\tz10_1 as string,\n\t\tz10_1_desc as string,\n\t\tz11_1 as string,\n\t\tz11_2 as string,\n\t\tz12_1 as string,\n\t\tz12_1_desc as string,\n\t\tz12_2 as string,\n\t\tz12_2_desc as string,\n\t\tz13_1 as string,\n\t\tz14_1 as string,\n\t\tz2_1 as string,\n\t\tz2_2 as string,\n\t\tz3_1 as string,\n\t\tz3_2 as string,\n\t\tz3_3 as string,\n\t\tz4_1 as string,\n\t\tz5_1 as string,\n\t\tz5_2 as string,\n\t\tz5_2_desc as string,\n\t\tz6_1 as string,\n\t\tz7_1 as string,\n\t\tz7_2 as string,\n\t\tz7_2_desc as string,\n\t\tz8_1 as string,\n\t\tz8_2 as string,\n\t\tz8_3 as string,\n\t\tz9_1 as string\n\t),\n\tallowSchemaDrift: true,\n\tvalidateSchema: false,\n\tignoreNoFilesFound: false) ~> OOBReport\nOOBReport select(mapColumn(\n\t\tVIIDWFGUID = VIIDWFGUID,\n\t\tTCOO = TCOO,\n\t\tCTO = CTO,\n\t\t{505_Indicator} = {505_Indicator},\n\t\t{505_Indicator__copy_} = {505_Indicator__copy_},\n\t\tAdj_Consequence_Model_Escalation_Date = Adj_Consequence_Model_Escalation_Date,\n\t\tADJUSTED_CM_DT = ADJUSTED_CM_DT,\n\t\tApplication_Support = Application_Support,\n\t\tApproved_Deferred_Remediation_Date = Approved_Deferred_Remediation_Date,\n\t\tApproved_Deferred_Remediation_Dt = Approved_Deferred_Remediation_Dt,\n\t\tAsset_Class = Asset_Class,\n\t\tAsset_SubClass = Asset_SubClass,\n\t\tASSET_CI_TYPE = ASSET_CI_TYPE,\n\t\tCI_Name = CI_Name,\n\t\tCIO_Direct_Org = CIO_Direct_Org,\n\t\tCM_Intake_Filter = CM_Intake_Filter,\n\t\tCM_Vulnerability_GroupID = CM_Vulnerability_GroupID,\n\t\tCM_CR_DATE = CM_CR_DATE,\n\t\tCM_INTAKE_DATE = CM_INTAKE_DATE,\n\t\tCM_Intake_Flag = CM_Intake_Flag,\n\t\tCM_PRE_EXCEPTION_NUMBER = CM_PRE_EXCEPTION_NUMBER,\n\t\tCM_VAT_FALSE_POSITIVE = CM_VAT_FALSE_POSITIVE,\n\t\tCompliance_Status = Compliance_Status,\n\t\tConsequence_Model_Escalation_Date = Consequence_Model_Escalation_Date,\n\t\tData_ID_concat = Data_ID_concat,\n\t\tData_Valid_Concat = Data_Valid_Concat,\n\t\tData_Validation_ID = Data_Validation_ID,\n\t\tDataSource = DataSource,\n\t\tDatasource_Check = Datasource_Check,\n\t\tDate_Logic = Date_Logic,\n\t\tDeferred_Remediation_Date = Deferred_Remediation_Date,\n\t\tDMAN_EVENT_PRIMARY_APP_NM = DMAN_EVENT_PRIMARY_APP_NM,\n\t\tDomain = Domain,\n\t\tDRD_Approval_Status = DRD_Approval_Status,\n\t\tDRD_Jira__ = DRD_Jira__,\n\t\tEscalation = Escalation,\n\t\tEscalation_Period = Escalation_Period,\n\t\tException_Number = Exception_Number,\n\t\tGame_Plan_Link = Game_Plan_Link,\n\t\tHPSA_Mesh_Details = HPSA_Mesh_Details,\n\t\tJAVA_PATH_ID = JAVA_PATH_ID,\n\t\tLast_Update_Date = Last_Update_Date,\n\t\tManaged_By = Managed_By,\n\t\tMiddleware_Support = Middleware_Support,\n\t\tNon_Path = Non_Path,\n\t\tNumber_of_Records = Number_of_Records,\n\t\tOS_Maintenance_Support = OS_Maintenance_Support,\n\t\tOverdueVulnInstanceCount = OverdueVulnInstanceCount,\n\t\tOwned_By = Owned_By,\n\t\tPAI_Flag = PAI_Flag,\n\t\tPath = Path,\n\t\tPath_Ind = Path_Ind,\n\t\tPath_Vuln_Chk = Path_Vuln_Chk,\n\t\tPath_ProductName = Path_ProductName,\n\t\tPending_Escalation = Pending_Escalation,\n\t\tPRB_Numb = PRB_Numb,\n\t\tPRB_Number = PRB_Number,\n\t\tPRM_ = PRM_,\n\t\tProduct_Name = Product_Name,\n\t\tPW_Exception_ID = PW_Exception_ID,\n\t\tPW_Expiration_Date = PW_Expiration_Date,\n\t\tPW_Expiration_Dt = PW_Expiration_Dt,\n\t\tPW_Overall_Status = PW_Overall_Status,\n\t\tQID = QID,\n\t\tQID_Title = QID_Title,\n\t\tQualysResults = QualysResults,\n\t\tQyls_First_Detected = Qyls_First_Detected,\n\t\tQyls_Last_Detected = Qyls_Last_Detected,\n\t\tQyls_Vuln_Status = Qyls_Vuln_Status,\n\t\tRC_Assignment = RC_Assignment,\n\t\tRC_Due_Date = RC_Due_Date,\n\t\tRecord_Creation_Date = Record_Creation_Date,\n\t\tRemed_CR_Number = Remed_CR_Number,\n\t\tREMED_COMPETENCY_CENTER_COMMENTS_DESC = REMED_COMPETENCY_CENTER_COMMENTS_DESC,\n\t\tREMED_QVRU_ASSET_CLASS_NM = REMED_QVRU_ASSET_CLASS_NM,\n\t\tREMED_RESEARCH_COMMENTS_DESC = REMED_RESEARCH_COMMENTS_DESC,\n\t\tREMED_VO_DATA_ISSUE_NM = REMED_VO_DATA_ISSUE_NM,\n\t\tRemediation_CR_Number = Remediation_CR_Number,\n\t\tReportRunDate = ReportRunDate,\n\t\tSN_CIO = SN_CIO,\n\t\tSN_LOB = SN_LOB,\n\t\tSN_Status = SN_Status,\n\t\tSN_CR_NUMBER = SN_CR_NUMBER,\n\t\tSolution_Plan = Solution_Plan,\n\t\tSolution_Plan_Indicator = Solution_Plan_Indicator,\n\t\tSpecial_Care_Add_Date = Special_Care_Add_Date,\n\t\tSystem_Role = System_Role,\n\t\tTarget_Remediation_Date = Target_Remediation_Date,\n\t\tTarget_Remediation_Dt = Target_Remediation_Dt,\n\t\tTechnology_Manager = Technology_Manager,\n\t\tToday_dt = Today_dt,\n\t\ttoday_ = today_,\n\t\tTSC_TECHNOPEDIA_ID = TSC_TECHNOPEDIA_ID,\n\t\tValidation_Description = Validation_Description,\n\t\tVersion = Version,\n\t\tVIID = VIID,\n\t\tVIIDWFGUID2 = VIIDWFGUID2,\n\t\tVIIDWFGUID___Path = VIIDWFGUID___Path,\n\t\tVIIDWFGUID___Path_Count = VIIDWFGUID___Path_Count,\n\t\tVIIDWFGUID_Path_Vulns = VIIDWFGUID_Path_Vulns,\n\t\tVIIDWFGUID_w_o_Path_Vulns = VIIDWFGUID_w_o_Path_Vulns,\n\t\tVIIDWFGUID_JAVAPATH = VIIDWFGUID_JAVAPATH,\n\t\tVMT_Competency = VMT_Competency,\n\t\tVO_Remediation_Status = VO_Remediation_Status,\n\t\tVO_Remediation_Type = VO_Remediation_Type,\n\t\tVO_Remediation_Type___VO_Remediation_Status = VO_Remediation_Type___VO_Remediation_Status,\n\t\tVO_Remediation_Type___VO_Rememdiation_Staus_Chk = VO_Remediation_Type___VO_Rememdiation_Staus_Chk,\n\t\tVULN_SUB_CATEGORY_NM = VULN_SUB_CATEGORY_NM,\n\t\tVulnerability_Type = Vulnerability_Type,\n\t\tVulnInstance_Count = VulnInstance_Count,\n\t\tWF_Fix = WF_Fix,\n\t\tWF_Rating = WF_Rating,\n\t\tWFGUID = WFGUID,\n\t\tWO_Number = WO_Number,\n\t\tWS_Workstream_Name = WS_Workstream_Name,\n\t\tWS_Workstream_POC = WS_Workstream_POC,\n\t\tYear_of_ReportRunDate = Year_of_ReportRunDate,\n\t\tZ_VulnType = Z_VulnType,\n\t\tz1_1 = z1_1,\n\t\tz1_2 = z1_2,\n\t\tz10_1 = z10_1,\n\t\tz10_1_desc = z10_1_desc,\n\t\tz11_1 = z11_1,\n\t\tz11_2 = z11_2,\n\t\tz12_1 = z12_1,\n\t\tz12_1_desc = z12_1_desc,\n\t\tz12_2 = z12_2,\n\t\tz12_2_desc = z12_2_desc,\n\t\tz13_1 = z13_1,\n\t\tz14_1 = z14_1,\n\t\tz2_1 = z2_1,\n\t\tz2_2 = z2_2,\n\t\tz3_1 = z3_1,\n\t\tz3_2 = z3_2,\n\t\tz3_3 = z3_3,\n\t\tz4_1 = z4_1,\n\t\tz5_1 = z5_1,\n\t\tz5_2 = z5_2,\n\t\tz5_2_desc = z5_2_desc,\n\t\tz6_1 = z6_1,\n\t\tz7_1 = z7_1,\n\t\tz7_2 = z7_2,\n\t\tz7_2_desc = z7_2_desc,\n\t\tz8_1 = z8_1,\n\t\tz8_2 = z8_2,\n\t\tz8_3 = z8_3,\n\t\tz9_1 = z9_1\n\t),\n\t skipDuplicateMapInputs: true,\n\t skipDuplicateMapOutputs: true) ~> DerivedColumn"
    }
  }
}