{
  "name" : "3_Refresh_WF_People",
  "type" : "Microsoft.DataFactory/factories/dataflows",
  "apiVersion" : "2018-06-01",
  "properties" : {
    "type" : "MappingDataFlow",
    "folder" : {
      "name" : "Wellfargo/"
    },
    "typeProperties" : {
      "sources" : [ {
        "name" : "GetHRCoreCommonUpdates",
        "dataset" : {
          "referenceName" : "Generic_OLEDB_DS_SRC",
          "type" : "DatasetReference"
        }
      } ],
      "sinks" : [ {
        "dataset" : {
          "referenceName" : "Generic_OLEDB_DS_TGT",
          "type" : "DatasetReference"
        },
        "name" : "OLEDBDestination"
      } ],
      "transformations" : [ ],
      "script" : "parameters{\n\tlastRefreshDateString as string ()\n}\n\nsource(output(\n\t\tLAST_NAME as string,\n\t\tSPRVS_ORG_LVL_03_NAME as string,\n\t\tSPRVS_ORG_LVL_04_NAME as string,\n\t\tEMPL_STATUS as string,\n\t\tIS_TCOO as integer,\n\t\tEMPLID as string,\n\t\tFIRST_NAME as string,\n\t\tSPRVS_ORG_LVL_03_MGR_NAME as string,\n\t\tSPRVS_ORG_LVL_04_MGR_NAME as string,\n\t\tIS_PLATFORM_APP_SVCS as integer,\n\t\tNAME as string,\n\t\tSPRVS_ORG_LVL_03_MGR_ID as integer,\n\t\tSPRVS_ORG_LVL_04_MGR_ID as integer,\n\t\tEMAIL_ID as string\n\t),\n\tallowSchemaDrift: true,\n\tvalidateSchema: false,\n\tisolationLevel: 'READ_UNCOMMITTED',\n\tquery: 'SELECT to_number(EMPLID) EMPLID     , PREF_FIRST_NAME || \\' \\' || PREF_LAST_NAME NAME     , PREF_FIRST_NAME FIRST_NAME     , PREF_LAST_NAME LAST_NAME     , EMAIL_ID     \t\t\t\t    , CASE \t\t\tWHEN (SPRVS_ORG_LVL_03_MGR_ID = \\'00002115460\\' OR SPRVS_ORG_LVL_06_MGR_ID = \\'00001672258\\') THEN 1 \t\t\tELSE 0  \t\t\tEND IS_TCOO         \t\t\t\t\t\t\t, CASE \t\t\tWHEN (SPRVS_ORG_LVL_04_MGR_ID = \\'00002086646\\' OR SPRVS_ORG_LVL_07_MGR_ID = \\'00002117751\\') THEN 1 \t\t\tELSE 0  \t\t\tEND IS_PLATFORM_APP_SVCS     , SPRVS_ORG_LVL_03_NAME     , SPRVS_ORG_LVL_03_MGR_NAME     , CASE      \tWHEN REGEXP_LIKE(SPRVS_ORG_LVL_03_MGR_ID, \\'^[[:digit:]]+$\\')     \tTHEN to_number(SPRVS_ORG_LVL_03_MGR_ID)      \tELSE NULL     \tEND SPRVS_ORG_LVL_03_MGR_ID     , SPRVS_ORG_LVL_04_NAME     , SPRVS_ORG_LVL_04_MGR_NAME     , CASE      \tWHEN REGEXP_LIKE(SPRVS_ORG_LVL_04_MGR_ID, \\'^[[:digit:]]+$\\')     \tTHEN to_number(SPRVS_ORG_LVL_04_MGR_ID)      \tELSE NULL     \tEND SPRVS_ORG_LVL_04_MGR_ID     , EMPL_STATUS      FROM DISTRIBUTION.VW_CORE_COMMON WHERE WHEN_CHANGED >= TO_DATE(\\'\\', \\'YYYYMMDD\\')',\n\tformat: 'query',\n\tstaged:false) ~> GetHRCoreCommonUpdates\nGetHRCoreCommonUpdates sink(input(\n\t\tlastName as string,\n\t\tlevel3Org as string,\n\t\tlevel4Org as string,\n\t\temployeeStatus as string,\n\t\tisTcoo as integer,\n\t\templId as integer,\n\t\tfirstName as string,\n\t\tlevel3Mgr as string,\n\t\tlevel4Mgr as string,\n\t\tisPlatformAppServices as integer,\n\t\tname as string,\n\t\tlevel3MgrEmplid as integer,\n\t\tlevel4MgrEmplid as integer,\n\t\temail as string\n\t),\n\tallowSchemaDrift: true,\n\tvalidateSchema: false,\n\tstagingSchemaName: 'dbo',\n\tsaveOrder: 10000,\n\tinsertable:true,\n\tdeletable:false,\n\tupsertable:false,\n\tupdateable:false,\n\tkeys:[],\n\tmapColumn(\n\t\tlastName = LAST_NAME,\n\t\tlevel3Org = SPRVS_ORG_LVL_03_NAME,\n\t\tlevel4Org = SPRVS_ORG_LVL_04_NAME,\n\t\temployeeStatus = EMPL_STATUS,\n\t\tisTcoo = IS_TCOO,\n\t\templId = EMPLID,\n\t\tfirstName = FIRST_NAME,\n\t\tlevel3Mgr = SPRVS_ORG_LVL_03_MGR_NAME,\n\t\tlevel4Mgr = SPRVS_ORG_LVL_04_MGR_NAME,\n\t\tisPlatformAppServices = IS_PLATFORM_APP_SVCS,\n\t\tname = NAME,\n\t\tlevel3MgrEmplid = SPRVS_ORG_LVL_03_MGR_ID,\n\t\tlevel4MgrEmplid = SPRVS_ORG_LVL_04_MGR_ID,\n\t\temail = EMAIL_ID)) ~> OLEDBDestination"
    }
  }
}