{
  "name" : "Data_Flow_Task1395_",
  "type" : "Microsoft.DataFactory/factories/dataflows",
  "apiVersion" : "2018-06-01",
  "properties" : {
    "type" : "MappingDataFlow",
    "folder" : {
      "name" : "SSISInventorysamples0716/"
    },
    "typeProperties" : {
      "sources" : [ {
        "name" : "OLEDBSource",
        "dataset" : {
          "referenceName" : "Generic_OLEDB_DS_SRC",
          "type" : "DatasetReference"
        }
      } ],
      "sinks" : [ {
        "dataset" : {
          "referenceName" : "Generic_OLEDB_DS_TGT",
          "type" : "DatasetReference"
        },
        "name" : "OLEDBDestination"
      } ],
      "transformations" : [ ],
      "script" : "parameters{\n\tAllChanges as string (),\n\tCombinedTable as string (),\n\tCurrentChangeID as string (),\n\tType1Table as string (),\n\tType2Table as string ()\n}\n\nsource(output(\n\t\t{} as string\n\t),\n\tallowSchemaDrift: true,\n\tvalidateSchema: false,\n\tisolationLevel: 'READ_UNCOMMITTED',\n\tquery: 'SELECT * , \\'Y\\' AS [IsCurrent] , GETDATE() AS [ETLDateCreated] FROM stg.ClientDimension  WHERE ClientID = ?',\n\tformat: 'query',\n\tstaged:false) ~> OLEDBSource\nOLEDBSource sink(input(\n\t\tSearchName as string,\n\t\tClientOfficeGroup as string,\n\t\tStmntStdMsg as boolean,\n\t\tClientPartnerStaffID as integer,\n\t\tEmailStatements as boolean,\n\t\tDefaultVATID as integer,\n\t\tClientManagerOfficeName as string,\n\t\tSageClient as boolean,\n\t\tClientManagerOfficeID as integer,\n\t\tMappedIndustry as string,\n\t\tCeaseDate as timestamp 'dd-MM-yyyy',\n\t\tTaxClient as boolean,\n\t\tStmntAgeMsg as boolean,\n\t\tNoStatement as boolean,\n\t\tClientManagerStaffID as integer,\n\t\tCreatedBy as integer,\n\t\tConsolidatedBilling as boolean,\n\t\tTotalCreditLimit as double,\n\t\tClientServiceLineGroupPartnerID as integer,\n\t\tTotalExposure as double,\n\t\tLTDRealisation as decimal(0,0),\n\t\tTelephone2 as string,\n\t\tCountry as string,\n\t\tPostCode as string,\n\t\tClientPartnerName as string,\n\t\tClientOfficeGroupPartnerID as integer,\n\t\tClientType as string,\n\t\tDoNotCall as boolean,\n\t\tLastDeEscalatedDate as timestamp 'dd-MM-yyyy',\n\t\tClientGroupID as integer,\n\t\tDefContactID as integer,\n\t\tReasonLost as string,\n\t\tEscalatedID as integer,\n\t\tIndustryCodeID as integer,\n\t\tURL as string,\n\t\tAddressDetail as string,\n\t\tFinanceCharge as boolean,\n\t\tClientRef as string,\n\t\tCreditControllerID as integer,\n\t\temail as string,\n\t\tManagerID as integer,\n\t\tFirstName as string,\n\t\tStateID as integer,\n\t\tClientPartnerOfficeID as integer,\n\t\tClientPartnerOfficeName as string,\n\t\tMobile as string,\n\t\tClientLimit as decimal(0,0),\n\t\tVATNo as string,\n\t\tNoBilling as boolean,\n\t\tClientJurisdiction as string,\n\t\tMappedNiche as string,\n\t\tInclude as boolean,\n\t\tCreateDate as timestamp 'dd-MM-yyyy',\n\t\tJurisdictionID as integer,\n\t\tIndustry as string,\n\t\tFAPPClient as boolean,\n\t\tNoAdminFee as boolean,\n\t\tDefInvFileName as string,\n\t\tCreditStatusID as integer,\n\t\tDateLost as timestamp 'dd-MM-yyyy',\n\t\tIndustryCode as integer,\n\t\tClientOfficeName as string,\n\t\tPartnerID as integer,\n\t\tMergedClientID as integer,\n\t\tMISDB as string,\n\t\tCity as string,\n\t\tEbilling as short,\n\t\tClientID as integer,\n\t\tEmailAddresses as string,\n\t\tIsCurrent as string,\n\t\tClientTypeID as integer,\n\t\tTelephone as string,\n\t\tClientOfficeGroupID as integer,\n\t\tOfficeID as integer,\n\t\tParentClientID as integer,\n\t\tClientJunxureID as integer,\n\t\tCounty as string,\n\t\tETLHashKey as string,\n\t\tYearEnd as timestamp 'dd-MM-yyyy',\n\t\tMaxExposure as decimal(0,0),\n\t\tClientContact as string,\n\t\tBillingNotes as string,\n\t\tSuspended as boolean,\n\t\tNotes as string,\n\t\tXClient as boolean,\n\t\tClientServiceLine as integer,\n\t\tClientStatus as string,\n\t\tClientServiceLineGroup as string,\n\t\tClientGroup as string,\n\t\tClientManagerName as string,\n\t\tContactID as integer,\n\t\tETLDateCreated as timestamp 'dd-MM-yyyy',\n\t\tParentClientSearchName as string,\n\t\tServiceLineID as integer,\n\t\tVATRegistered as boolean,\n\t\tAvgDaysToPay as short,\n\t\tClientStatusID as integer,\n\t\tParentClientFirstName as string,\n\t\tFax as string,\n\t\tClientServiceLineGroupID as integer\n\t),\n\tallowSchemaDrift: true,\n\tvalidateSchema: false,\n\tstagingSchemaName: 'dbo',\n\tsaveOrder: 10000,\n\tinsertable:true,\n\tdeletable:false,\n\tupsertable:false,\n\tupdateable:false,\n\tkeys:[],\n\tmapColumn(\n\t\tSearchName,\n\t\tClientOfficeGroup,\n\t\tStmntStdMsg,\n\t\tClientPartnerStaffID,\n\t\tEmailStatements,\n\t\tDefaultVATID,\n\t\tClientManagerOfficeName,\n\t\tSageClient,\n\t\tClientManagerOfficeID,\n\t\tMappedIndustry,\n\t\tCeaseDate,\n\t\tTaxClient,\n\t\tStmntAgeMsg,\n\t\tNoStatement,\n\t\tClientManagerStaffID,\n\t\tCreatedBy,\n\t\tConsolidatedBilling,\n\t\tTotalCreditLimit,\n\t\tClientServiceLineGroupPartnerID,\n\t\tTotalExposure,\n\t\tLTDRealisation,\n\t\tTelephone2,\n\t\tCountry,\n\t\tPostCode,\n\t\tClientPartnerName,\n\t\tClientOfficeGroupPartnerID,\n\t\tClientType,\n\t\tDoNotCall,\n\t\tLastDeEscalatedDate,\n\t\tClientGroupID,\n\t\tDefContactID,\n\t\tReasonLost,\n\t\tEscalatedID,\n\t\tIndustryCodeID,\n\t\tURL,\n\t\tAddressDetail,\n\t\tFinanceCharge,\n\t\tClientRef,\n\t\tCreditControllerID,\n\t\temail,\n\t\tManagerID,\n\t\tFirstName,\n\t\tStateID,\n\t\tClientPartnerOfficeID,\n\t\tClientPartnerOfficeName,\n\t\tMobile,\n\t\tClientLimit,\n\t\tVATNo,\n\t\tNoBilling,\n\t\tClientJurisdiction,\n\t\tMappedNiche,\n\t\tInclude,\n\t\tCreateDate,\n\t\tJurisdictionID,\n\t\tIndustry,\n\t\tFAPPClient,\n\t\tNoAdminFee,\n\t\tDefInvFileName,\n\t\tCreditStatusID,\n\t\tDateLost,\n\t\tIndustryCode,\n\t\tClientOfficeName,\n\t\tPartnerID,\n\t\tMergedClientID,\n\t\tMISDB,\n\t\tCity,\n\t\tEbilling,\n\t\tClientID,\n\t\tEmailAddresses,\n\t\tIsCurrent,\n\t\tClientTypeID,\n\t\tTelephone,\n\t\tClientOfficeGroupID,\n\t\tOfficeID,\n\t\tParentClientID,\n\t\tClientJunxureID,\n\t\tCounty,\n\t\tETLHashKey,\n\t\tYearEnd,\n\t\tMaxExposure,\n\t\tClientContact,\n\t\tBillingNotes,\n\t\tSuspended,\n\t\tNotes,\n\t\tXClient,\n\t\tClientServiceLine,\n\t\tClientStatus,\n\t\tClientServiceLineGroup,\n\t\tClientGroup,\n\t\tClientManagerName,\n\t\tContactID,\n\t\tETLDateCreated,\n\t\tParentClientSearchName,\n\t\tServiceLineID,\n\t\tVATRegistered,\n\t\tAvgDaysToPay,\n\t\tClientStatusID,\n\t\tParentClientFirstName,\n\t\tFax,\n\t\tClientServiceLineGroupID)) ~> OLEDBDestination"
    }
  }
}