{
  "name" : "PPL_SII_Vuln_Email_Alerts",
  "type" : "Microsoft.DataFactory/factories/pipelines",
  "apiVersion" : "2018-06-01",
  "properties" : {
    "activities" : [ {
      "name" : "Execute_SQL_Task_151__SCRIPT",
      "type" : "Script",
      "policy" : null,
      "dependsOn" : [ ],
      "state" : null,
      "description" : null,
      "onInactiveMarkAs" : null,
      "linkedServiceName" : {
        "referenceName" : "AzureSqlDatabase1",
        "type" : "LinkedServiceReference"
      },
      "typeProperties" : {
        "scripts" : [ {
          "type" : "Query",
          "text" : "select\ncase when count(*)   > 0 then 0 else 1 end as flag\nfrom tbl_SII_Vuln_History_Alerts\nwhere cast(Import_Date as date) = cast(getdate() as date)"
        } ],
        "scriptBlockExecutionTimeout" : null
      }
    }, {
      "name" : "0_Execute_SQL_Task_151__VA",
      "type" : "SetVariable",
      "policy" : {
        "timeout" : "00:30:00",
        "retry" : 0,
        "retryIntervalInSeconds" : 0,
        "secureOutput" : false,
        "secureInput" : false
      },
      "dependsOn" : [ {
        "activity" : "Execute_SQL_Task_151__SCRIPT",
        "dependencyConditions" : [ "Succeeded" ]
      } ],
      "state" : null,
      "description" : null,
      "onInactiveMarkAs" : null,
      "typeProperties" : {
        "variableName" : "TodaysData",
        "value" : "@activity('Execute_SQL_Task_151__SCRIPT').output.resultSets[0].rows[0].[0]"
      }
    }, {
      "name" : "IFACTIVITY_Insert_Email_Records52__Insert_Records_",
      "type" : "IfCondition",
      "policy" : null,
      "dependsOn" : [ {
        "activity" : "0_Execute_SQL_Task_151__VA",
        "dependencyConditions" : [ "Succeeded" ]
      } ],
      "state" : null,
      "description" : null,
      "onInactiveMarkAs" : null,
      "typeProperties" : {
        "expression" : {
          "value" : "@equals(variables('TodaysData'),1)",
          "type" : "Expression"
        },
        "ifFalseActivities" : [ {
          "name" : "Collect_Daily_SII_Metric50_",
          "type" : "ExecuteDataFlow",
          "policy" : null,
          "dependsOn" : [ ],
          "state" : null,
          "description" : null,
          "onInactiveMarkAs" : null,
          "typeProperties" : {
            "dataflow" : {
              "referenceName" : "Collect_Daily_SII_Metric50_",
              "type" : "DataFlowReference",
              "parameters" : {
                "TodaysData" : {
                  "type" : "Expression",
                  "value" : "0"
                }
              },
              "datasetParameters" : {
                "DailySIIMetricView" : {
                  "TableName" : {
                    "value" : "vw_SII_EmailAlerts_Details",
                    "type" : "Expression"
                  },
                  "Schema" : {
                    "value" : "dbo",
                    "type" : "Expression"
                  },
                  "Container" : {
                    "value" : "",
                    "type" : "Expression"
                  },
                  "FileName" : {
                    "value" : "Daily SII Metric View",
                    "type" : "Expression"
                  },
                  "Directory" : {
                    "value" : null,
                    "type" : "Expression"
                  },
                  "ColumnDelimiter" : ","
                },
                "tblSIIVulnHistoryAlerts" : {
                  "TableName" : {
                    "value" : "tbl_SII_Vuln_History_Alerts",
                    "type" : "Expression"
                  },
                  "Schema" : {
                    "value" : "dbo",
                    "type" : "Expression"
                  },
                  "Container" : {
                    "value" : "",
                    "type" : "Expression"
                  },
                  "FileName" : {
                    "value" : null,
                    "type" : "Expression"
                  },
                  "Directory" : {
                    "value" : null,
                    "type" : "Expression"
                  },
                  "ColumnDelimiter" : ","
                }
              }
            },
            "compute" : null,
            "staging" : { }
          }
        }, {
          "name" : "Only_Send_once_a_week54__SCRIPT",
          "type" : "Script",
          "policy" : null,
          "dependsOn" : [ {
            "activity" : "Collect_Daily_SII_Metric50_",
            "dependencyConditions" : [ "Succeeded" ]
          } ],
          "state" : null,
          "description" : null,
          "onInactiveMarkAs" : null,
          "linkedServiceName" : {
            "referenceName" : "AzureSqlDatabase1",
            "type" : "LinkedServiceReference"
          },
          "typeProperties" : {
            "scripts" : [ {
              "type" : "Query",
              "text" : "\ndeclare @upddatedate date = (select \n\ncase \nwhen isHoliday = 0\nand DATENAME(weekday,getdate()) <> 'Monday' then CurrentDate\nelse null end as updatedate\n\nfrom Calendar\nwhere currentdate =cast( getdate() as date)\n)\n\n;\nupdate tbl_ssis_utility \nset SendDate = @upddatedate \nwhere SendDate is null \n\n\n\n"
            } ],
            "scriptBlockExecutionTimeout" : null
          }
        } ],
        "ifTrueActivities" : [ {
          "name" : "Insert_Email_Records52__Insert_Records_into_Email_",
          "type" : "Script",
          "policy" : null,
          "dependsOn" : [ ],
          "state" : null,
          "description" : null,
          "onInactiveMarkAs" : null,
          "linkedServiceName" : {
            "referenceName" : "AzureSqlDatabase1",
            "type" : "LinkedServiceReference"
          },
          "typeProperties" : {
            "scripts" : [ {
              "type" : "Query",
              "text" : "  insert into [PLHS].[dbo].[tbl_ssis_utility]\n  (\t'michael.dematos@wellsfargo.com'\t[To]\n      ,[Subject]\n      ,[body]\n      ,[ReceiveDate]\n      ,[SendDate]\n      ,[BodyFormat]\n      ,null [CC]\n\t  )\n  \n  select \n  [To_],\n  [subject_],\n  [body],\n getdate() [RECEIVEDATE],\n  null,\n  2,\n  [CC]\n     \n  from \n  [PLHS].[dbo].[vw_SII_EmailAlerts_Daily_v2]\n\nwhere   [To_]  IS NOT NULL \nGO\n\n"
            } ],
            "scriptBlockExecutionTimeout" : null
          }
        } ]
      }
    } ],
    "folder" : {
      "name" : "Wellfargo_0707/COO_VulnPackages"
    },
    "parameters" : { },
    "variables" : {
      "TodaysData" : {
        "type" : "Integer",
        "defaultValue" : "0"
      }
    }
  }
}